wc_utils/__init__.py
wc_utils/_version.py
wc_utils/cache.py
wc_utils/quilt.py
wc_utils/config/__init__.py
wc_utils/config/core.default.cfg
wc_utils/config/core.py
wc_utils/config/core.schema.cfg
wc_utils/data_logs/__init__.py
wc_utils/debug_logs/__init__.py
wc_utils/debug_logs/config.default.cfg
wc_utils/debug_logs/config.py
wc_utils/debug_logs/config.schema.cfg
wc_utils/debug_logs/core.py
wc_utils/util/__init__.py
wc_utils/util/decorate_default_data_struct.py
wc_utils/util/dict.py
wc_utils/util/enumerate.py
wc_utils/util/environ.py
wc_utils/util/files.py
wc_utils/util/git.py
wc_utils/util/list.py
wc_utils/util/misc.py
wc_utils/util/rand.py
wc_utils/util/stats.py
wc_utils/util/string.py
wc_utils/util/testing.py
wc_utils/util/types.py
wc_utils/util/uniform_seq.py
wc_utils/util/units.py
wc_utils/util/units.txt
wc_utils/util/chem/DrawMolecule.jar
wc_utils/util/chem/DrawMolecule.java
wc_utils/util/chem/GetMajorMicroSpecies.jar
wc_utils/util/chem/GetMajorMicroSpecies.java
wc_utils/util/chem/__init__.py
wc_utils/util/chem/core.py
wc_utils/util/chem/marvin.py
wc_utils/util/ontology/__init__.py
wc_utils/util/ontology/core.py
wc_utils/workbook/__init__.py
wc_utils/workbook/core.py
wc_utils/workbook/io.py
wc_utils-0.0.24.dist-info/LICENSE
wc_utils-0.0.24.dist-info/METADATA
wc_utils-0.0.24.dist-info/WHEEL
wc_utils-0.0.24.dist-info/top_level.txt
wc_utils-0.0.24.dist-info/RECORD
